TFilterPy/__init__.py
TFilterPy/module_functions.py
TFilterPy-0.1.dist-info/LICENSE
TFilterPy-0.1.dist-info/METADATA
TFilterPy-0.1.dist-info/WHEEL
TFilterPy-0.1.dist-info/top_level.txt
TFilterPy-0.1.dist-info/RECORD
