Metadata-Version: 2.1
Name: TFilterPy
Version: 0.1
Summary: A short description of your module
Home-page: https://github.com/leparalamapara/FilterPY
Author: Thabang L. Mashinini- Sekgoto Lebogang M. Mashinini-Sekgoto
Author-email: thabangline@gmail.com
Classifier: Development Status :: 3 - Alpha
Classifier: Intended Audience :: Developers
Classifier: License :: OSI Approved :: MIT License
Classifier: Programming Language :: Python :: 3
Classifier: Programming Language :: Python :: 3.6
Classifier: Programming Language :: Python :: 3.7
Classifier: Programming Language :: Python :: 3.8
License-File: LICENSE
Requires-Dist: numpy
Requires-Dist: scipy
